Metadata-Version: 1.0
Name: instagramPictures
Version: 1.2
Summary: Script for downloading pictures from instagram.com
Home-page: https://github.com/fiterV/instagramPictures
Author: Vadym Prokopets
Author-email: vadym_prokopec@mail.ru
License: UNKNOWN
Keywords: instagram,pictures,download
Platform: UNKNOWN
